py_auto_env/__init__.py
py_auto_env/loader.py
py_auto_env-0.1.1.dist-info/METADATA
py_auto_env-0.1.1.dist-info/WHEEL
py_auto_env-0.1.1.dist-info/RECORD
